mef_tools/__init__.py
mef_tools/io.py
mef_tools/test/__init__.py
mef_tools/test/test_io.py
mef_tools-1.2.3.dist-info/LICENSE
mef_tools-1.2.3.dist-info/METADATA
mef_tools-1.2.3.dist-info/WHEEL
mef_tools-1.2.3.dist-info/top_level.txt
mef_tools-1.2.3.dist-info/RECORD
